camino/__init__.py
camino-1.7.0.dist-info/LICENSE
camino-1.7.0.dist-info/METADATA
camino-1.7.0.dist-info/WHEEL
camino-1.7.0.dist-info/top_level.txt
camino-1.7.0.dist-info/RECORD
