Metadata-Version: 2.1
Name: camino
Version: 1.7.0
Summary: A library for controlling an Arduino from Python over Serial
Home-page: https://github.com/n-wach/camino
Author: Nathan Wachholz
Author-email: camino@nathanwachholz.com
Classifier: Programming Language :: Python :: 3
Classifier: License :: OSI Approved :: MIT License
Classifier: Operating System :: OS Independent
Requires-Python: >=3.6
License-File: LICENSE
Requires-Dist: pyserial
